__init__.py
optimizo.py
classes/__init__.py
classes/add_instruction.py
classes/bootstrap.py
classes/minify.py
classes/run_instructions.py
optimizo-1.3.dist-info/METADATA
optimizo-1.3.dist-info/WHEEL
optimizo-1.3.dist-info/top_level.txt
optimizo-1.3.dist-info/RECORD
