Metadata-Version: 2.1
Name: optimizo
Version: 1.3
Summary: Optimizo its an tool that allows to set up instructions and run them later. In the mean you will have to run them manually
Home-page: http://taku.co.zw
Author: Takunda Madechangu
Author-email: madechangu.takunda@gmail.com
License: MIT
Platform: UNKNOWN
Requires-Dist: appdirs (==1.4.4)
Requires-Dist: autopep8 (==1.5.7)
Requires-Dist: css-html-js-minify (==2.5.5)
Requires-Dist: distlib (==0.3.2)
Requires-Dist: filelock (==3.0.12)
Requires-Dist: pycodestyle (==2.7.0)
Requires-Dist: six (==1.16.0)
Requires-Dist: tinydb (==4.5.0)
Requires-Dist: toml (==0.10.2)
Requires-Dist: virtualenv (==20.4.7)
Requires-Dist: virtualenvwrapper-win (==1.2.6)
